conv_allocator/__init__.py
conv_allocator/allocator.py
conv_allocator/allocator_test.py
conv_allocator/um_accessors.py
conv_allocator-3.17.1.dist-info/METADATA
conv_allocator-3.17.1.dist-info/WHEEL
conv_allocator-3.17.1.dist-info/entry_points.txt
conv_allocator-3.17.1.dist-info/top_level.txt
conv_allocator-3.17.1.dist-info/RECORD
