Metadata-Version: 2.1
Name: conv-allocator
Version: 3.17.1
Requires-Dist: ortools==9.9.3963
Requires-Dist: protobuf==4.25.5
Requires-Dist: uni-model==10.0.23
